common/__init__.py
common/cli.py
common/constants.py
common/ini.py
common/udptools.py
common/utils.py
common/scratch/__init__.py
common/scratch/multicast.py
common/scratch/replace_stdout.py
common/scratch/sockets.py
common/scratch/test_decorator.py
blowpipe_common-0.0.3.dist-info/LICENSE.txt
blowpipe_common-0.0.3.dist-info/METADATA
blowpipe_common-0.0.3.dist-info/WHEEL
blowpipe_common-0.0.3.dist-info/top_level.txt
blowpipe_common-0.0.3.dist-info/RECORD
